_northroot/__init__.py
_northroot/_northroot.abi3.so
northroot-0.1.1.dist-info/METADATA
northroot-0.1.1.dist-info/WHEEL
northroot-0.1.1.dist-info/RECORD
