Metadata-Version: 2.4
Name: northroot
Version: 0.1.1
Classifier: Development Status :: 3 - Alpha
Classifier: Intended Audience :: Developers
Classifier: License :: OSI Approved :: Apache Software License
Classifier: Programming Language :: Python :: 3
Classifier: Programming Language :: Python :: 3.10
Classifier: Programming Language :: Python :: 3.11
Classifier: Programming Language :: Python :: 3.12
Classifier: Programming Language :: Rust
Classifier: Topic :: Software Development :: Libraries :: Python Modules
Classifier: Topic :: System :: Distributed Computing
Classifier: Topic :: System :: Logging
Requires-Dist: opentelemetry-api>=1.20.0 ; extra == 'otel'
Requires-Dist: maturin>=1.0,<2.0 ; extra == 'dev'
Requires-Dist: pytest>=7.0.0 ; extra == 'dev'
Requires-Dist: pytest-asyncio>=0.21.0 ; extra == 'dev'
Requires-Dist: black>=23.0.0 ; extra == 'dev'
Requires-Dist: mypy>=1.0.0 ; extra == 'dev'
Requires-Dist: ruff>=0.1.0 ; extra == 'dev'
Provides-Extra: otel
Provides-Extra: dev
Summary: Python SDK providing high-level bindings to the Northroot Engine. Record work, verify receipts, and manage proof storage with simple async/sync APIs.
Keywords: proof,verification,compute,receipt,delta-compute,data-shapes,observability,audit
Author: Northroot Contributors
License: Apache-2.0
Requires-Python: >=3.10
Project-URL: Homepage, https://github.com/Northroot-Labs/northroot
Project-URL: Documentation, https://docs.northroot.dev
Project-URL: Repository, https://github.com/Northroot-Labs/northroot
